thomas/core/__build__
thomas/core/__init__.py
thomas/core/_options.py
thomas/core/_version.py
thomas/core/error.py
thomas/core/examples.py
thomas/core/util.py
thomas/core/data/TNM7_subnet.oobn
thomas/core/data/TNM_explains_death_after_training_with_TNM7_priors_resampled_Hugin.oobn
thomas/core/data/TNM_explains_death_before_training_with_TNM7_priors.oobn
thomas/core/data/dataset_17_2.csv
thomas/core/data/dataset_17_2_with_NAs.csv
thomas/core/data/dataset_17_3.csv
thomas/core/data/lungcancer.json
thomas/core/data/lungcancer.net
thomas/core/data/lungcancer.oobn
thomas/core/data/oobn.lark
thomas/core/data/prostatecancer.oobn
thomas/core/data/sprinkler-D_BC.json
thomas/core/data/sprinkler.json
thomas/core/data/student.json
thomas/core/factors/__init__.py
thomas/core/factors/cpt.py
thomas/core/factors/factor.py
thomas/core/factors/jpt.py
thomas/core/learn/__init__.py
thomas/core/models/__init__.py
thomas/core/models/bag.py
thomas/core/models/base.py
thomas/core/models/jpt.py
thomas/core/models/bn/__init__.py
thomas/core/models/bn/bayesian_network.py
thomas/core/models/bn/discrete_node.py
thomas/core/models/bn/node.py
thomas/core/models/junction_tree/__init__.py
thomas/core/models/junction_tree/junction_tree.py
thomas/core/models/junction_tree/tree_edge.py
thomas/core/models/junction_tree/tree_node.py
thomas/core/reader/__init__.py
thomas/core/reader/base.py
thomas/core/reader/net.py
thomas/core/reader/oobn.py
thomas_core-0.1.3.dist-info/LICENSE
thomas_core-0.1.3.dist-info/METADATA
thomas_core-0.1.3.dist-info/WHEEL
thomas_core-0.1.3.dist-info/top_level.txt
thomas_core-0.1.3.dist-info/RECORD
