Metadata-Version: 2.1
Name: thomas-core
Version: 0.1.3
Summary: Thomas, a library for working with Bayesian Networks.
Home-page: https://github.com/mellesies/thomas-core
Author: Melle Sieswerda
Author-email: m.sieswerda@iknl.nl
License: UNKNOWN
Platform: UNKNOWN
Classifier: Programming Language :: Python :: 3
Classifier: License :: OSI Approved :: MIT License
Classifier: Operating System :: OS Independent
Requires-Python: >= 3.7
Requires-Dist: lark-parser
Requires-Dist: matplotlib (>=3.1)
Requires-Dist: networkx (>=2.4)
Requires-Dist: numpy (>=1.18)
Requires-Dist: pandas (>=1)
Requires-Dist: termcolor
